fastbootpy/__init__.py
fastbootpy/exceptions.py
fastbootpy/fastboot_device.py
fastbootpy/fastboot_manager.py
fastbootpy/fastboot_protocol.py
fastbootpy/i_fastboot_device.py
fastbootpy/i_fastboot_manager.py
fastbootpy/i_fastboot_protocol.py
fastbootpy/i_usb_device.py
fastbootpy/usb_device.py
fastbootpy-0.4.1.dist-info/WHEEL
fastbootpy-0.4.1.dist-info/METADATA
fastbootpy-0.4.1.dist-info/RECORD
