Metadata-Version: 2.1
Name: fastbootpy
Version: 0.4.1
Summary: 
Home-page: https://github.com/WorkHardes/fastbootpy
Keywords: fastboot,usb,android
Author: Orekhov Arkady
Author-email: arckadyor34@google.com
Requires-Python: >=3.8,<4.0
Classifier: Development Status :: 1 - Planning
Classifier: Programming Language :: Python :: 3
Classifier: Programming Language :: Python :: 3.8
Classifier: Programming Language :: Python :: 3.9
Classifier: Programming Language :: Python :: 3.10
Classifier: Programming Language :: Python :: 3
Classifier: Programming Language :: Python :: 3.10
Classifier: Topic :: Software Development
Classifier: Topic :: Software Development :: Libraries
Classifier: Topic :: Software Development :: Libraries :: Python Modules
Classifier: Typing :: Typed
Requires-Dist: pyusb (>=1.2.1,<2.0.0)
Project-URL: Documentation, https://github.com/WorkHardes/fastbootpy
Project-URL: Repository, https://github.com/WorkHardes/fastbootpy
